e2vec/__init__.py
e2vec/audio_embedding.py
e2vec/image_embedding.py
e2vec/nlp_embedding.py
e2vec-0.5.0.dist-info/WHEEL
e2vec-0.5.0.dist-info/METADATA
e2vec-0.5.0.dist-info/RECORD
