Metadata-Version: 2.1
Name: e2vec
Version: 0.5.0
Summary: 
Author: An Pham
Author-email: ancs21.ps@gmail.com
Requires-Python: >=3.9,<4.0
Classifier: Programming Language :: Python :: 3
Classifier: Programming Language :: Python :: 3.10
Classifier: Programming Language :: Python :: 3.9
Requires-Dist: sentence-transformers (>=2.2.0,<3.0.0)
Requires-Dist: timm (>=0.5.4,<0.6.0)
Requires-Dist: torchaudio (>=0.11.0,<0.12.0)
